{
  "$schema": "./templates.schema.json",
  "categories": [
    {
      "slug": "backend-applications",
      "name": "Backend Applications",
      "description": "API and service starters for FastAPI and similar Python backends.",
      "details": "Use when the deliverable is an HTTP API or background worker \u2014 FastAPI for async APIs with OpenAPI docs.",
      "labels": [
        "Backend",
        "API",
        "Python",
        "FastAPI"
      ]
    },
    {
      "slug": "ci",
      "name": "CI",
      "description": "Continuous integration and repository automation.",
      "details": "GitHub Actions, Dependabot, and related repository workflows.",
      "labels": [
        "CI",
        "GitHub",
        "DevOps"
      ]
    },
    {
      "slug": "containers",
      "name": "Containers",
      "description": "Docker and Compose packaging for the app.",
      "details": "Add when you want container images and compose stacks for the API.",
      "labels": [
        "Docker",
        "Compose",
        "DevOps"
      ]
    },
    {
      "slug": "database",
      "name": "Database",
      "description": "Database services and connection scaffolding.",
      "details": "Pair with the app when you need Postgres (or similar) locally/in compose.",
      "labels": [
        "PostgreSQL",
        "Database"
      ]
    },
    {
      "slug": "editor",
      "name": "Editor",
      "description": "Editor and remote development ergonomics.",
      "details": "Dev Containers and related IDE integrations.",
      "labels": [
        "DevContainer",
        "VS Code"
      ]
    },
    {
      "slug": "cli-applications",
      "name": "CLI Applications",
      "description": "Command-line tools and console scripts.",
      "details": "Use for Typer/Click CLIs and internal utilities shipped as entry points.",
      "labels": [
        "CLI",
        "Python",
        "Typer"
      ]
    },
    {
      "slug": "observability",
      "name": "Observability",
      "description": "Error tracking, metrics, and tracing integrations.",
      "details": "Add when you need production diagnostics such as Sentry.",
      "labels": [
        "Observability",
        "Sentry",
        "Monitoring"
      ]
    },
    {
      "slug": "security",
      "name": "Security",
      "description": "Authentication and authorization scaffolds.",
      "details": "JWT/session auth skeletons and related security helpers.",
      "labels": [
        "Auth",
        "JWT",
        "Security"
      ]
    }
  ],
  "templates": [
    {
      "name": "FastAPI Starter",
      "slug": "fastapi-starter",
      "description": "Production-ready FastAPI API with uv, Ruff, pytest, mypy, pyright, and pydantic-settings",
      "url": "https://github.com/Create-Python-App/cpa-templates?subdir=templates/fastapi-starter",
      "type": "fastapi-backend",
      "category": "backend-applications",
      "labels": [
        "FastAPI",
        "API",
        "Python",
        "uv",
        "Backend",
        "Type Hints",
        "mypy",
        "pyright"
      ]
    },
    {
      "name": "CLI Starter",
      "slug": "cli-starter",
      "description": "Typer CLI with uv, Ruff, pytest, and a console script entry point",
      "url": "https://github.com/Create-Python-App/cpa-templates?subdir=templates/cli-starter",
      "type": "cli-app",
      "category": "cli-applications",
      "labels": [
        "CLI",
        "Typer",
        "Python",
        "uv"
      ]
    },
    {
      "name": "Celery Worker",
      "slug": "celery-worker",
      "description": "Celery worker with Redis defaults, pydantic-settings, and eager-mode tests",
      "url": "https://github.com/Create-Python-App/cpa-templates?subdir=templates/celery-worker",
      "type": "celery-worker",
      "category": "backend-applications",
      "labels": [
        "Celery",
        "Worker",
        "Redis",
        "Python",
        "uv"
      ]
    },
    {
      "name": "Django API",
      "slug": "django-api",
      "description": "Django + DRF API starter with uv, Ruff, pytest-django, and health probes",
      "url": "https://github.com/Create-Python-App/cpa-templates?subdir=templates/django-api",
      "type": "django-backend",
      "category": "backend-applications",
      "labels": [
        "Django",
        "DRF",
        "API",
        "Python",
        "uv"
      ]
    }
  ],
  "extensions": [
    {
      "name": "GitHub Setup",
      "slug": "github-setup",
      "description": "GitHub Actions CI, MegaLinter, Danger PR review, todo-to-issue, Dependabot, and issue/PR templates",
      "url": "https://github.com/Create-Python-App/cpa-templates?subdir=extensions/github-setup",
      "type": [
        "celery-worker",
        "cli-app",
        "django-backend",
        "fastapi-backend"
      ],
      "category": "ci",
      "labels": [
        "GitHub",
        "CI",
        "DevOps",
        "MegaLinter",
        "Danger"
      ]
    },
    {
      "name": "Python Docker",
      "slug": "python-docker",
      "description": "Dockerfile, compose.yml, and compose.prod.yml for local and containerized runs",
      "url": "https://github.com/Create-Python-App/cpa-templates?subdir=extensions/python-docker",
      "type": [
        "celery-worker",
        "cli-app",
        "fastapi-backend"
      ],
      "category": "containers",
      "labels": [
        "Docker",
        "DevOps",
        "Container"
      ]
    },
    {
      "name": "Python Postgres",
      "slug": "python-postgres",
      "description": "PostgreSQL service under docker/postgres/compose.yml plus env examples",
      "url": "https://github.com/Create-Python-App/cpa-templates?subdir=extensions/python-postgres",
      "type": [
        "celery-worker",
        "django-backend",
        "fastapi-backend"
      ],
      "category": "database",
      "labels": [
        "PostgreSQL",
        "Database",
        "Docker"
      ]
    },
    {
      "name": "Python Dev Container",
      "slug": "python-devcontainer",
      "description": "VS Code Dev Container with Python 3.12 and uv",
      "url": "https://github.com/Create-Python-App/cpa-templates?subdir=extensions/python-devcontainer",
      "type": [
        "celery-worker",
        "cli-app",
        "django-backend",
        "fastapi-backend"
      ],
      "category": "editor",
      "labels": [
        "DevContainer",
        "VS Code",
        "uv"
      ]
    },
    {
      "name": "Python SQLAlchemy",
      "slug": "python-sqlalchemy",
      "description": "SQLAlchemy 2.x session helpers and Alembic migrations for FastAPI",
      "url": "https://github.com/Create-Python-App/cpa-templates?subdir=extensions/python-sqlalchemy",
      "type": [
        "fastapi-backend"
      ],
      "category": "database",
      "labels": [
        "SQLAlchemy",
        "Alembic",
        "ORM",
        "Database"
      ]
    },
    {
      "name": "Python Redis",
      "slug": "python-redis",
      "description": "Redis client helper and local Compose service",
      "url": "https://github.com/Create-Python-App/cpa-templates?subdir=extensions/python-redis",
      "type": [
        "fastapi-backend"
      ],
      "category": "database",
      "labels": [
        "Redis",
        "Cache",
        "Queue"
      ]
    },
    {
      "name": "Python Sentry",
      "slug": "python-sentry",
      "description": "Sentry SDK for FastAPI with env-driven init helper",
      "url": "https://github.com/Create-Python-App/cpa-templates?subdir=extensions/python-sentry",
      "type": [
        "fastapi-backend"
      ],
      "category": "observability",
      "labels": [
        "Sentry",
        "Observability",
        "Errors"
      ]
    },
    {
      "name": "Python Auth JWT",
      "slug": "python-auth-jwt",
      "description": "JWT auth feature skeleton with password hashing helpers",
      "url": "https://github.com/Create-Python-App/cpa-templates?subdir=extensions/python-auth-jwt",
      "type": [
        "fastapi-backend"
      ],
      "category": "security",
      "labels": [
        "Auth",
        "JWT",
        "Security"
      ]
    }
  ]
}
